sawmill/__init__.py
sawmill/_version.py
sawmill/compatibility.py
sawmill/log.py
sawmill/configurator/__init__.py
sawmill/configurator/alpha.py
sawmill/configurator/classic.py
sawmill/filterer/__init__.py
sawmill/filterer/base.py
sawmill/filterer/item.py
sawmill/filterer/level.py
sawmill/filterer/pattern.py
sawmill/formatter/__init__.py
sawmill/formatter/base.py
sawmill/formatter/email.py
sawmill/formatter/field.py
sawmill/formatter/mustache.py
sawmill/formatter/template.py
sawmill/handler/__init__.py
sawmill/handler/base.py
sawmill/handler/buffer.py
sawmill/handler/distribute.py
sawmill/handler/email.py
sawmill/handler/stream.py
sawmill/logger/__init__.py
sawmill/logger/audit.py
sawmill/logger/base.py
sawmill/logger/classic.py
sawmill/logger/dynamic.py
sawmill/logger/traceback.py
sawmill-0.2.1.dist-info/DESCRIPTION.rst
sawmill-0.2.1.dist-info/METADATA
sawmill-0.2.1.dist-info/RECORD
sawmill-0.2.1.dist-info/WHEEL
sawmill-0.2.1.dist-info/metadata.json
sawmill-0.2.1.dist-info/top_level.txt
