Metadata-Version: 2.0
Name: sawmill
Version: 0.2.1
Summary: Alternative logging framework for Python
Home-page: http://gitlab.com/4degrees/sawmill
Author: Martin Pengelly-Phillips
Author-email: martin@4degrees.ltd.uk
License: Apache License (2.0)
Keywords: logging
Platform: UNKNOWN
Requires-Dist: html2text (>=2016.4.2,<2016.5)
Requires-Dist: pystache (>=0.5,<0.6)
Provides-Extra: dev
Requires-Dist: lowdown (>=0.1.0,<2); extra == 'dev'
Requires-Dist: pytest (>=2.9,<3); extra == 'dev'
Requires-Dist: pytest-cov (<3,>=2); extra == 'dev'
Requires-Dist: pytest-mock (>=0.11,<1); extra == 'dev'
Requires-Dist: pytest-runner (>=2.7,<3); extra == 'dev'
Requires-Dist: sphinx (>=1.2.2,<2); extra == 'dev'
Requires-Dist: sphinx-rtd-theme (>=0.1.6,<1); extra == 'dev'
Provides-Extra: setup
Requires-Dist: lowdown (>=0.1.0,<2); extra == 'setup'
Requires-Dist: pytest-runner (>=2.7,<3); extra == 'setup'
Requires-Dist: sphinx (>=1.2.2,<2); extra == 'setup'
Requires-Dist: sphinx-rtd-theme (>=0.1.6,<1); extra == 'setup'
Provides-Extra: tests
Requires-Dist: pytest (>=2.9,<3); extra == 'tests'
Requires-Dist: pytest-cov (<3,>=2); extra == 'tests'
Requires-Dist: pytest-mock (>=0.11,<1); extra == 'tests'
